pytest_alerts/__init__.py
pytest_alerts/core.py
pytest_alerts/slack.py
pytest_alerts/telegram.py
pytest_alerts-1.6.1.dist-info/METADATA
pytest_alerts-1.6.1.dist-info/WHEEL
pytest_alerts-1.6.1.dist-info/entry_points.txt
pytest_alerts-1.6.1.dist-info/licenses/LICENSE
pytest_alerts-1.6.1.dist-info/RECORD
