Metadata-Version: 2.4
Name: pytest-alerts
Version: 1.6.1
Summary: A pytest plugin for sending test results to Slack and Telegram
Project-URL: Homepage, https://github.com/nikolaout/pytest-alerts
Project-URL: Repository, https://github.com/nikolaout/pytest-alerts.git
Project-URL: Documentation, https://github.com/nikolaout/pytest-alerts#readme
Project-URL: Changelog, https://github.com/nikolaout/pytest-alerts/blob/main/CHANGELOG.md
Project-URL: Issues, https://github.com/nikolaout/pytest-alerts/issues
Author-email: Nikola <nikolaoutwork@gmail.com>
License: pytest-alerts License
License-File: LICENSE
Keywords: alerts,notifications,pytest,slack,telegram
Classifier: Development Status :: 4 - Beta
Classifier: Framework :: Pytest
Classifier: Intended Audience :: Developers
Classifier: License :: OSI Approved :: MIT License
Classifier: Natural Language :: English
Classifier: Operating System :: OS Independent
Classifier: Programming Language :: Python :: 3.8
Classifier: Programming Language :: Python :: 3.9
Classifier: Programming Language :: Python :: 3.10
Classifier: Programming Language :: Python :: 3.11
Classifier: Topic :: Software Development :: Testing
Requires-Python: >=3.8
Requires-Dist: pytest>=7.4.0
Requires-Dist: requests>=2.26.0
Requires-Dist: typing-extensions>=4.9.0; python_version < '3.10'
Provides-Extra: dev
Requires-Dist: black>=22.3.0; extra == 'dev'
Requires-Dist: build>=1.2.2.post1; extra == 'dev'
Requires-Dist: pytest-cov>=5.0.0; extra == 'dev'
Requires-Dist: twine>=6.1.0; extra == 'dev'
